blaster_logger/__init__.py
blaster_logger/log.py
blaster_logger-0.1.0.dist-info/WHEEL
blaster_logger-0.1.0.dist-info/METADATA
blaster_logger-0.1.0.dist-info/RECORD
