Metadata-Version: 2.1
Name: blaster-logger
Version: 0.1.0
Summary: 
Home-page: https://github.com/Blasterai/blaster-logger
Author: MB
Author-email: mb@blaster.ai
Requires-Python: >=3.7,<4.0
Classifier: Programming Language :: Python :: 3
Classifier: Programming Language :: Python :: 3.7
Requires-Dist: loguru (>=0.3.2,<0.4.0)
